batterysim/__init__.py
batterysim/model.py
batterysim/mosaik.py
mosaik_batterysim-1.0.0.dist-info/METADATA
mosaik_batterysim-1.0.0.dist-info/RECORD
mosaik_batterysim-1.0.0.dist-info/WHEEL
mosaik_batterysim-1.0.0.dist-info/entry_points.txt
mosaik_batterysim-1.0.0.dist-info/top_level.txt
tests/__init__.py
tests/test_model.py
tests/test_mosaik.py
